fink_tns/__init__.py
fink_tns/report.py
fink_tns/utils.py
fink_tns-0.14.dist-info/LICENSE
fink_tns-0.14.dist-info/METADATA
fink_tns-0.14.dist-info/WHEEL
fink_tns-0.14.dist-info/top_level.txt
fink_tns-0.14.dist-info/RECORD
