Metadata-Version: 2.1
Name: fink-tns
Version: 0.14
Summary: Push Fink candidates to TNS.
Author: JulienPeloton
Author-email: peloton@lal.in2p3.fr
Project-URL: Documentation, https://fink-broker.org
Project-URL: Source, https://github.com/astrolabsoftware/fink-tns
Classifier: Programming Language :: Python :: 3.6
Classifier: Programming Language :: Python :: 3.7
Classifier: License :: OSI Approved :: Apache Software License
Classifier: Operating System :: Unix
Classifier: Development Status :: 4 - Beta
Classifier: Intended Audience :: Science/Research
License-File: LICENSE
